azure/security/attestation/__init__.py
azure/security/attestation/_administration_client.py
azure/security/attestation/_client.py
azure/security/attestation/_common.py
azure/security/attestation/_configuration.py
azure/security/attestation/_models.py
azure/security/attestation/_version.py
azure/security/attestation/_generated/__init__.py
azure/security/attestation/_generated/_azure_attestation_rest_client.py
azure/security/attestation/_generated/_configuration.py
azure/security/attestation/_generated/_version.py
azure/security/attestation/_generated/aio/__init__.py
azure/security/attestation/_generated/aio/_azure_attestation_rest_client.py
azure/security/attestation/_generated/aio/_configuration.py
azure/security/attestation/_generated/aio/operations/__init__.py
azure/security/attestation/_generated/aio/operations/_attestation_operations.py
azure/security/attestation/_generated/aio/operations/_metadata_configuration_operations.py
azure/security/attestation/_generated/aio/operations/_policy_certificates_operations.py
azure/security/attestation/_generated/aio/operations/_policy_operations.py
azure/security/attestation/_generated/aio/operations/_signing_certificates_operations.py
azure/security/attestation/_generated/models/__init__.py
azure/security/attestation/_generated/models/_azure_attestation_rest_client_enums.py
azure/security/attestation/_generated/models/_models.py
azure/security/attestation/_generated/models/_models_py3.py
azure/security/attestation/_generated/operations/__init__.py
azure/security/attestation/_generated/operations/_attestation_operations.py
azure/security/attestation/_generated/operations/_metadata_configuration_operations.py
azure/security/attestation/_generated/operations/_policy_certificates_operations.py
azure/security/attestation/_generated/operations/_policy_operations.py
azure/security/attestation/_generated/operations/_signing_certificates_operations.py
azure/security/attestation/aio/__init__.py
azure_security_attestation-1.0.0.dist-info/METADATA
azure_security_attestation-1.0.0.dist-info/WHEEL
azure_security_attestation-1.0.0.dist-info/top_level.txt
azure_security_attestation-1.0.0.dist-info/RECORD
